aws_resource_search/__init__.py
aws_resource_search/_version.py
aws_resource_search/api.py
aws_resource_search/ars.py
aws_resource_search/ars_base.py
aws_resource_search/ars_def.py
aws_resource_search/ars_init.py
aws_resource_search/ars_mixin.py
aws_resource_search/ars_search_patterns.py
aws_resource_search/base_model.py
aws_resource_search/base_searcher.py
aws_resource_search/compat.py
aws_resource_search/downloader.py
aws_resource_search/exc.py
aws_resource_search/logger.py
aws_resource_search/model.py
aws_resource_search/paths.py
aws_resource_search/res_lib.py
aws_resource_search/searcher_enum.py
aws_resource_search/searcher_finder.py
aws_resource_search/searcher_metadata.py
aws_resource_search/searchers.json
aws_resource_search/searchers.py
aws_resource_search/searchers_enum.py
aws_resource_search/terminal.py
aws_resource_search/ui_def.py
aws_resource_search/ui_init.py
aws_resource_search/utils.py
aws_resource_search/cli/__init__.py
aws_resource_search/cli/clear.py
aws_resource_search/cli/main.py
aws_resource_search/cli/which.py
aws_resource_search/code/__init__.py
aws_resource_search/code/ars.py.jinja
aws_resource_search/code/ars_mixin.py.jinja
aws_resource_search/code/gen_code.py
aws_resource_search/code/implemented_aws_resource_types.rst.jinja
aws_resource_search/code/searcher_enum.json
aws_resource_search/code/searcher_enum.py.jinja
aws_resource_search/code/searchers.py.jinja
aws_resource_search/code/searchers_enum.json
aws_resource_search/code/searchers_enum.py.jinja
aws_resource_search/code/searchers_index.rst.jinja
aws_resource_search/conf/__init__.py
aws_resource_search/conf/define.py
aws_resource_search/conf/init.py
aws_resource_search/docs/__init__.py
aws_resource_search/documents/__init__.py
aws_resource_search/documents/api.py
aws_resource_search/documents/base_document.py
aws_resource_search/documents/resource_document.py
aws_resource_search/documents/resource_type_document.py
aws_resource_search/handlers/__init__.py
aws_resource_search-0.6.2.dist-info/AUTHORS.rst
aws_resource_search-0.6.2.dist-info/LICENSE.txt
aws_resource_search-0.6.2.dist-info/METADATA
aws_resource_search-0.6.2.dist-info/WHEEL
aws_resource_search-0.6.2.dist-info/entry_points.txt
aws_resource_search-0.6.2.dist-info/top_level.txt
aws_resource_search-0.6.2.dist-info/RECORD
