Metadata-Version: 2.1
Name: aws_resource_search
Version: 0.6.2
Summary: A terminal application that enables interactive searches for AWS resources. It is a mini AWS console in your terminal or shell environment.
Home-page: https://github.com/MacHu-GWU/aws_resource_search-project
Download-URL: https://pypi.python.org/pypi/aws_resource_search/0.6.2#downloads
Author: Sanhe Hu
Author-email: husanhe@gmail.com
Maintainer: Sanhe Hu
Maintainer-email: husanhe@gmail.com
License: GPL
Platform: Windows
Platform: MacOS
Platform: Unix
Classifier: Development Status :: 4 - Beta
Classifier: Intended Audience :: Developers
Classifier: License :: OSI Approved :: GNU General Public License (GPL)
Classifier: Natural Language :: English
Classifier: Operating System :: Microsoft :: Windows
Classifier: Operating System :: MacOS
Classifier: Operating System :: Unix
Classifier: Programming Language :: Python
Classifier: Programming Language :: Python :: 3.7
Classifier: Programming Language :: Python :: 3.8
Classifier: Programming Language :: Python :: 3.9
Classifier: Programming Language :: Python :: 3.10
Classifier: Programming Language :: Python :: 3.11
Classifier: Programming Language :: Python :: 3.12
Classifier: Programming Language :: Python :: 3 :: Only
Requires-Python: >=3.7
License-File: LICENSE.txt
License-File: AUTHORS.rst
Requires-Dist: pathlib-mate <2.0.0,>=1.3.2
Requires-Dist: iterproxy <1.0.0,>=0.3.1
Requires-Dist: sayt <1.0.0,>=0.6.5
Requires-Dist: boto-session-manager <2.0.0,>=1.7.2
Requires-Dist: aws-console-url <2.0.0,>=1.4.1
Requires-Dist: aws-arns <2.0.0,>=1.4.3
Requires-Dist: jmespath <2.0.0,>=1.0.1
Requires-Dist: zelfred <1.0.0,>=0.4.1
Requires-Dist: pyperclip <2.0.0,>=1.8.2
Requires-Dist: fire <1.0.0,>=0.1.3
Requires-Dist: awscli-mate <2.0.0,>=1.1.2
Requires-Dist: cached-property >=1.5.2 ; python_version < "3.8"
Requires-Dist: typing-extensions <4.7.0,>=4.6.0 ; python_version < "3.8"
Provides-Extra: docs
Requires-Dist: Sphinx ==5.3.0 ; extra == 'docs'
Requires-Dist: sphinx-jinja ==2.0.2 ; extra == 'docs'
Requires-Dist: sphinx-copybutton ==0.5.1 ; extra == 'docs'
Requires-Dist: sphinx-design ==0.5.0 ; extra == 'docs'
Requires-Dist: furo ==2023.03.27 ; extra == 'docs'
Requires-Dist: nbsphinx ==0.8.12 ; extra == 'docs'
Requires-Dist: rstobj ==1.2.1 ; extra == 'docs'
Requires-Dist: pygments ==2.15.1 ; extra == 'docs'
Requires-Dist: ipython ==8.10.0 ; extra == 'docs'
Requires-Dist: docfly ==2.0.1 ; extra == 'docs'
Provides-Extra: tests
Requires-Dist: pytest ; extra == 'tests'
Requires-Dist: pytest-cov ; extra == 'tests'
Requires-Dist: moto ; extra == 'tests'
Requires-Dist: moto[all] ; extra == 'tests'
Requires-Dist: fixa <1.0.0,>=0.10.2 ; extra == 'tests'
Requires-Dist: Faker ; extra == 'tests'
Requires-Dist: rich ; extra == 'tests'
